<?xml version="1.0" encoding="utf-8" ?><dwsync><file name="ie7-5.gif" server="framework.camiloo.co.uk//var/www/vhosts/camiloo.co.uk/framework/" local="3390746346" remote="20570615530" /><file name="firefox.png" server="framework.camiloo.co.uk//var/www/vhosts/camiloo.co.uk/framework/" local="3390746346" remote="20570615530" /><file name="ie6-2.gif" server="framework.camiloo.co.uk//var/www/vhosts/camiloo.co.uk/framework/" local="3390746346" remote="20570615530" /><file name="ie7-1.gif" server="framework.camiloo.co.uk//var/www/vhosts/camiloo.co.uk/framework/" local="3390746346" remote="20570615530" /><file name="ie7-2.gif" server="framework.camiloo.co.uk//var/www/vhosts/camiloo.co.uk/framework/" local="3390746346" remote="20570615530" /><file name="ie7-6.gif" server="framework.camiloo.co.uk//var/www/vhosts/camiloo.co.uk/framework/" local="3390746346" remote="20570615530" /><file name="ie6-1.gif" server="framework.camiloo.co.uk//var/www/vhosts/camiloo.co.uk/framework/" local="3390746346" remote="20570615530" /><file name="opera.png" server="framework.camiloo.co.uk//var/www/vhosts/camiloo.co.uk/framework/" local="3390746346" remote="20570615530" /><file name="ie7-4.gif" server="framework.camiloo.co.uk//var/www/vhosts/camiloo.co.uk/framework/" local="3390746346" remote="20570615530" /><file name="ie7-3.gif" server="framework.camiloo.co.uk//var/www/vhosts/camiloo.co.uk/framework/" local="3390746346" remote="20570615530" /></dwsync>