<?xml version="1.0" encoding="utf-8" ?><dwsync><file name="Dashboard.php" server="framework.camiloo.co.uk//var/www/vhosts/camiloo.co.uk/framework/" local="3390746351" remote="20570615535" /><file name="Messages.php" server="framework.camiloo.co.uk//var/www/vhosts/camiloo.co.uk/framework/" local="3390746351" remote="20570615535" /><file name="Cache.php" server="framework.camiloo.co.uk//var/www/vhosts/camiloo.co.uk/framework/" local="3390746351" remote="20570615535" /><file name="Sitemap.php" server="framework.camiloo.co.uk//var/www/vhosts/camiloo.co.uk/framework/" local="3390746351" remote="20570615535" /><file name="Backup.php" server="framework.camiloo.co.uk//var/www/vhosts/camiloo.co.uk/framework/" local="3390746351" remote="20570615535" /><file name="Template.php" server="framework.camiloo.co.uk//var/www/vhosts/camiloo.co.uk/framework/" local="3390746351" remote="20570615535" /><file name="Denied.php" server="framework.camiloo.co.uk//var/www/vhosts/camiloo.co.uk/framework/" local="3390746351" remote="20570615535" /><file name="Abstract.php" server="framework.camiloo.co.uk//var/www/vhosts/camiloo.co.uk/framework/" local="3390746351" remote="20570615535" /><file name="Widget.php" server="framework.camiloo.co.uk//var/www/vhosts/camiloo.co.uk/framework/" local="3390746351" remote="20570615535" /><file name="User.php" server="framework.camiloo.co.uk//var/www/vhosts/camiloo.co.uk/framework/" local="3390746351" remote="20570615535" /><file name="Urlrewrite.php" server="framework.camiloo.co.uk//var/www/vhosts/camiloo.co.uk/framework/" local="3390746351" remote="20570615535" /><file name="Page.php" server="framework.camiloo.co.uk//var/www/vhosts/camiloo.co.uk/framework/" local="3390746351" remote="20570615535" /></dwsync>